configurationpy/__init__.py
configurationpy/configurationpy.py
Configurationpy-0.3.dist-info/LICENSE
Configurationpy-0.3.dist-info/METADATA
Configurationpy-0.3.dist-info/WHEEL
Configurationpy-0.3.dist-info/top_level.txt
Configurationpy-0.3.dist-info/RECORD
