Metadata-Version: 2.1
Name: Configurationpy
Version: 0.3
Summary: A cool module for configuration, port of Conf.rb, my other library: https://rubygems.org/gems/confrb
Home-page: https://gitlab.com/Gsbhasin84/configurationpy
Author: Gurjus Bhasin
Author-email: gsbhasin84@gmail.com
License: MIT
Platform: UNKNOWN
Classifier: Programming Language :: Python :: 3
Classifier: License :: OSI Approved :: MIT License
Classifier: Operating System :: OS Independent
Requires-Python: >=3.0
Requires-Dist: pyyaml
